gprlibpy/__init__.py
gprlibpy/cli.py
gprlibpy/core/__init__.py
gprlibpy/core/adapters.py
gprlibpy/core/dataset.py
gprlibpy/core/scan.py
gprlibpy/core/utils.py
gprlibpy/utils/__init__.py
gprlibpy/utils/file_utils.py
gprlibpy/utils/image_utils.py
gprlibpy/utils/lib_utils.py
gprlibpy/widgets/__init__.py
gprlibpy/widgets/map_viewer/__init__.py
gprlibpy/widgets/map_viewer/gmap_index.html
gprlibpy/widgets/map_viewer/map_elements.py
gprlibpy/widgets/map_viewer/map_viewer.py
gprlibpy-0.2.20.dist-info/METADATA
gprlibpy-0.2.20.dist-info/WHEEL
gprlibpy-0.2.20.dist-info/entry_points.txt
gprlibpy-0.2.20.dist-info/RECORD
