Metadata-Version: 2.4
Name: gprlibpy
Version: 0.2.20
Summary: A Python library to manipulate and visualize GPR data from GPR-Studio
Requires-Python: >=3.10
Requires-Dist: dask[complete]>=2024.10.0
Requires-Dist: geopandas>=1.0.1
Requires-Dist: graphviz>=0.20.3
Requires-Dist: lgopy
Requires-Dist: opencv-python>=4.10.0.84
Requires-Dist: openpyxl>=3.1.5
Requires-Dist: rich>=13.9.3
Requires-Dist: skyio
Requires-Dist: tqdm>=4.66.5
Requires-Dist: typer>=0.15.1
Requires-Dist: validators>=0.34.0
Requires-Dist: zarr>=2.18.3
Provides-Extra: gprstudio-blocks
Requires-Dist: gprblocks; extra == 'gprstudio-blocks'
Provides-Extra: gprstudio-io
Requires-Dist: gprio; extra == 'gprstudio-io'
Provides-Extra: widgets
Requires-Dist: pyqt6-webengine>=6.8.0; extra == 'widgets'
Requires-Dist: pyqt6>=6.8.1; extra == 'widgets'
